README.rst
setup.py
stuff_proxy.egg-info/PKG-INFO
stuff_proxy.egg-info/SOURCES.txt
stuff_proxy.egg-info/dependency_links.txt
stuff_proxy.egg-info/entry_points.txt
stuff_proxy.egg-info/not-zip-safe
stuff_proxy.egg-info/requires.txt
stuff_proxy.egg-info/top_level.txt
stuffproxy/__init__.py
stuffproxy/cli.py
stuffproxy/config.py
stuffproxy/menu.py
stuffproxy/server.py
stuffproxy/utils.py
stuffproxy/templates/nginx.conf
stuffproxy/templates/supervisor.conf
stuffproxy/templates/uwsgi.ini