Metadata-Version: 1.1
Name: stuff-proxy
Version: 0.1.1
Summary: UNKNOWN
Home-page: https://github.com/phpdude/stuff-proxy
Author: Alexandr I. Shurigin
Author-email: alexandr.shurigin@gmail.com
License: GPL
Platform: UNKNOWN
Classifier: Development Status :: 4 - Beta
